.DS_Store
easy_log/__init__.py
easy_log/ai_task_generator.py
easy_log/bitbucket.py
easy_log/cli.py
easy_log/cm_automation.py
easy_log/config_gen.py
easy_log/custom_key_gen.py
easy_log/jira_task_creator.py
ssl_log/__init__.py
ssl_log/ai_task_generator.py
ssl_log/bitbucket.py
ssl_log/cli.py
ssl_log/config_gen.py
ssl_log/custom_key_gen.py
ssl_log/jira_task_creator.py
ssl_log-1.0.1.dist-info/METADATA
ssl_log-1.0.1.dist-info/WHEEL
ssl_log-1.0.1.dist-info/entry_points.txt
ssl_log-1.0.1.dist-info/top_level.txt
ssl_log-1.0.1.dist-info/RECORD
