Metadata-Version: 2.1
Name: ssl-log
Version: 1.0.1
Summary: A CLI tool to automate logging tasks from Bitbucket to Jira.
Home-page: https://github.com/AscEmon/SSLlog
Author: Abu Sayed Chowdhury
Author-email: sayem227@gmail.com
License: UNKNOWN
Platform: UNKNOWN
Classifier: Programming Language :: Python :: 3
Classifier: License :: OSI Approved :: MIT License
Classifier: Operating System :: OS Independent
Requires-Python: >=3.6
Requires-Dist: requests
